busybeaver/__init__.py
busybeaver/busybeaver.py
busybeaver/constants.py
busybeaver/operations.py
busybeaver-0.0.4.dist-info/LICENSE
busybeaver-0.0.4.dist-info/METADATA
busybeaver-0.0.4.dist-info/WHEEL
busybeaver-0.0.4.dist-info/top_level.txt
busybeaver-0.0.4.dist-info/RECORD
