Metadata-Version: 2.1
Name: busybeaver
Version: 0.0.4
Summary: simplify post-processing of MIKE model results into GIS formats.
Home-page: https://github.com/murray91/busybeaver
Author: Ryan Murray
Author-email: ryanwaltermurray@gmail.com
License: UNKNOWN
Keywords: MIKE post-processing water modelling
Platform: UNKNOWN
Classifier: Development Status :: 3 - Alpha
Classifier: License :: OSI Approved :: MIT License
Classifier: Programming Language :: Python :: 3
Requires-Python: >=3.8
